{
	"$schema": "http://schema.management.azure.com/schemas/2015-01-01/deploymentTemplate.json#",
	"contentVersion": "1.0.0.0",
	"parameters": {
		"factoryName": {
			"type": "string",
			"metadata": "Data Factory name",
			"defaultValue": "datafactory1982sd2"
		},
		"AzureBlobStorage1_connectionString": {
			"type": "secureString",
			"metadata": "Secure string for 'connectionString' of 'AzureBlobStorage1'"
		},
		"AzureSqlDatabase1_connectionString": {
			"type": "secureString",
			"metadata": "Secure string for 'connectionString' of 'AzureSqlDatabase1'"
		},
		"StorageAccount_accountKey": {
			"type": "secureString",
			"metadata": "Secure string for 'accountKey' of 'StorageAccount'"
		},
		"RestService1_properties_typeProperties_url": {
			"type": "string",
			"defaultValue": "https://github.com/deekondasathish/sathishETL/blob/main/sample.txt"
		},
		"StorageAccount_properties_typeProperties_url": {
			"type": "string",
			"defaultValue": "https://storageaccount1982sd.dfs.core.windows.net/"
		},
		"EventTrigger_properties_typeProperties_scope": {
			"type": "string",
			"defaultValue": "/subscriptions/80ea84e8-afce-4851-928a-9e2219724c69/resourceGroups/1-07fcdc76-playground-sandbox/providers/Microsoft.Storage/storageAccounts/storageaccount1982sd"
		}
	},
	"variables": {
		"factoryId": "[concat('Microsoft.DataFactory/factories/', parameters('factoryName'))]"
	},
	"resources": [
		{
			"name": "[concat(parameters('factoryName'), '/pipeline1')]",
			"type": "Microsoft.DataFactory/factories/pipelines",
			"apiVersion": "2018-06-01",
			"properties": {
				"activities": [
					{
						"name": "Wait1",
						"type": "Wait",
						"dependsOn": [],
						"userProperties": [],
						"typeProperties": {
							"waitTimeInSeconds": 1
						}
					}
				],
				"policy": {
					"elapsedTimeMetric": {},
					"cancelAfter": {}
				},
				"annotations": []
			},
			"dependsOn": []
		},
		{
			"name": "[concat(parameters('factoryName'), '/pipeline3')]",
			"type": "Microsoft.DataFactory/factories/pipelines",
			"apiVersion": "2018-06-01",
			"properties": {
				"activities": [
					{
						"name": "load persons",
						"type": "ExecuteDataFlow",
						"dependsOn": [],
						"policy": {
							"timeout": "0.12:00:00",
							"retry": 0,
							"retryIntervalInSeconds": 30,
							"secureOutput": false,
							"secureInput": false
						},
						"userProperties": [],
						"typeProperties": {
							"dataflow": {
								"referenceName": "personload",
								"type": "DataFlowReference",
								"parameters": {},
								"datasetParameters": {
									"sourcepersons": {},
									"sink1": {}
								}
							},
							"staging": {},
							"compute": {
								"coreCount": 8,
								"computeType": "General"
							},
							"traceLevel": "Fine"
						}
					}
				],
				"policy": {
					"elapsedTimeMetric": {},
					"cancelAfter": {}
				},
				"annotations": []
			},
			"dependsOn": [
				"[concat(variables('factoryId'), '/dataflows/personload')]"
			]
		},
		{
			"name": "[concat(parameters('factoryName'), '/TargetDB_persons')]",
			"type": "Microsoft.DataFactory/factories/datasets",
			"apiVersion": "2018-06-01",
			"properties": {
				"linkedServiceName": {
					"referenceName": "AzureSqlDatabase1",
					"type": "LinkedServiceReference"
				},
				"annotations": [],
				"type": "AzureSqlTable",
				"schema": [
					{
						"name": "fname",
						"type": "varchar"
					},
					{
						"name": "lname",
						"type": "varchar"
					}
				],
				"typeProperties": {
					"schema": "dbo",
					"table": "persons"
				}
			},
			"dependsOn": [
				"[concat(variables('factoryId'), '/linkedServices/AzureSqlDatabase1')]"
			]
		},
		{
			"name": "[concat(parameters('factoryName'), '/persons')]",
			"type": "Microsoft.DataFactory/factories/datasets",
			"apiVersion": "2018-06-01",
			"properties": {
				"linkedServiceName": {
					"referenceName": "StorageAccount",
					"type": "LinkedServiceReference"
				},
				"annotations": [],
				"type": "DelimitedText",
				"typeProperties": {
					"location": {
						"type": "AzureBlobFSLocation",
						"fileName": "Persons.txt",
						"fileSystem": "container1982sdsource"
					},
					"columnDelimiter": ",",
					"escapeChar": "\\",
					"firstRowAsHeader": true,
					"quoteChar": "\""
				},
				"schema": [
					{
						"name": "fname",
						"type": "String"
					},
					{
						"name": "lname",
						"type": "String"
					}
				]
			},
			"dependsOn": [
				"[concat(variables('factoryId'), '/linkedServices/StorageAccount')]"
			]
		},
		{
			"name": "[concat(parameters('factoryName'), '/AzureBlobStorage1')]",
			"type": "Microsoft.DataFactory/factories/linkedServices",
			"apiVersion": "2018-06-01",
			"properties": {
				"annotations": [],
				"type": "AzureBlobStorage",
				"typeProperties": {
					"connectionString": "[parameters('AzureBlobStorage1_connectionString')]"
				}
			},
			"dependsOn": []
		},
		{
			"name": "[concat(parameters('factoryName'), '/AzureSqlDatabase1')]",
			"type": "Microsoft.DataFactory/factories/linkedServices",
			"apiVersion": "2018-06-01",
			"properties": {
				"annotations": [],
				"type": "AzureSqlDatabase",
				"typeProperties": {
					"connectionString": "[parameters('AzureSqlDatabase1_connectionString')]"
				}
			},
			"dependsOn": []
		},
		{
			"name": "[concat(parameters('factoryName'), '/RestService1')]",
			"type": "Microsoft.DataFactory/factories/linkedServices",
			"apiVersion": "2018-06-01",
			"properties": {
				"annotations": [],
				"type": "RestService",
				"typeProperties": {
					"url": "[parameters('RestService1_properties_typeProperties_url')]",
					"enableServerCertificateValidation": true,
					"authenticationType": "Anonymous"
				}
			},
			"dependsOn": []
		},
		{
			"name": "[concat(parameters('factoryName'), '/StorageAccount')]",
			"type": "Microsoft.DataFactory/factories/linkedServices",
			"apiVersion": "2018-06-01",
			"properties": {
				"annotations": [],
				"type": "AzureBlobFS",
				"typeProperties": {
					"url": "[parameters('StorageAccount_properties_typeProperties_url')]",
					"accountKey": {
						"type": "SecureString",
						"value": "[parameters('StorageAccount_accountKey')]"
					}
				}
			},
			"dependsOn": []
		},
		{
			"name": "[concat(parameters('factoryName'), '/EventTrigger')]",
			"type": "Microsoft.DataFactory/factories/triggers",
			"apiVersion": "2018-06-01",
			"properties": {
				"annotations": [],
				"runtimeState": "Started",
				"pipelines": [
					{
						"pipelineReference": {
							"referenceName": "pipeline3",
							"type": "PipelineReference"
						},
						"parameters": {}
					}
				],
				"type": "BlobEventsTrigger",
				"typeProperties": {
					"blobPathBeginsWith": "/container1982sdsource/blobs/triggerfile",
					"ignoreEmptyBlobs": false,
					"scope": "[parameters('EventTrigger_properties_typeProperties_scope')]",
					"events": [
						"Microsoft.Storage.BlobCreated"
					]
				}
			},
			"dependsOn": [
				"[concat(variables('factoryId'), '/pipelines/pipeline3')]"
			]
		},
		{
			"name": "[concat(parameters('factoryName'), '/EveryMin')]",
			"type": "Microsoft.DataFactory/factories/triggers",
			"apiVersion": "2018-06-01",
			"properties": {
				"annotations": [],
				"runtimeState": "Started",
				"pipelines": [
					{
						"pipelineReference": {
							"referenceName": "pipeline3",
							"type": "PipelineReference"
						},
						"parameters": {}
					}
				],
				"type": "ScheduleTrigger",
				"typeProperties": {
					"recurrence": {
						"frequency": "Minute",
						"interval": 2,
						"startTime": "2023-08-09T03:17:00Z",
						"timeZone": "UTC"
					}
				}
			},
			"dependsOn": [
				"[concat(variables('factoryId'), '/pipelines/pipeline3')]"
			]
		},
		{
			"name": "[concat(parameters('factoryName'), '/personload')]",
			"type": "Microsoft.DataFactory/factories/dataflows",
			"apiVersion": "2018-06-01",
			"properties": {
				"type": "MappingDataFlow",
				"typeProperties": {
					"sources": [
						{
							"dataset": {
								"referenceName": "persons",
								"type": "DatasetReference"
							},
							"name": "sourcepersons"
						}
					],
					"sinks": [
						{
							"dataset": {
								"referenceName": "TargetDB_persons",
								"type": "DatasetReference"
							},
							"name": "sink1"
						}
					],
					"transformations": [],
					"scriptLines": [
						"source(output(",
						"          fname as string,",
						"          lname as string",
						"     ),",
						"     allowSchemaDrift: true,",
						"     validateSchema: false,",
						"     ignoreNoFilesFound: false) ~> sourcepersons",
						"sourcepersons sink(allowSchemaDrift: true,",
						"     validateSchema: false,",
						"     input(",
						"          fname as string,",
						"          lname as string",
						"     ),",
						"     deletable:false,",
						"     insertable:true,",
						"     updateable:false,",
						"     upsertable:false,",
						"     format: 'table',",
						"     skipDuplicateMapInputs: true,",
						"     skipDuplicateMapOutputs: true,",
						"     errorHandlingOption: 'stopOnFirstError') ~> sink1"
					]
				}
			},
			"dependsOn": [
				"[concat(variables('factoryId'), '/datasets/persons')]",
				"[concat(variables('factoryId'), '/datasets/TargetDB_persons')]"
			]
		}
	]
}